poeditorexporter.py
poeditorexporter-1.0.1.dist-info/LICENSE.md
poeditorexporter-1.0.1.dist-info/METADATA
poeditorexporter-1.0.1.dist-info/WHEEL
poeditorexporter-1.0.1.dist-info/top_level.txt
poeditorexporter-1.0.1.dist-info/RECORD
