Metadata-Version: 2.1
Name: poeditorexporter
Version: 1.0.1
Summary: CLI package to export poeditor translations
Home-page: https://github.com/mivek/poeditor_exporter
Author: Jean-Kevin KPADEY
Author-email: jeankevin@gmail.com
License: MIT
Keywords: poeditor exporter
Platform: UNKNOWN
Classifier: Programming Language :: Python :: 3
Classifier: License :: OSI Approved :: MIT License
Classifier: Operating System :: OS Independent
Requires-Python: >=3.6
Requires-Dist: requests
